watchinotify/__init__.py
watchinotify/inotify.py
watchinotify-0.1.0.dist-info/licenses/LICENSE
watchinotify-0.1.0.dist-info/METADATA
watchinotify-0.1.0.dist-info/WHEEL
watchinotify-0.1.0.dist-info/top_level.txt
watchinotify-0.1.0.dist-info/RECORD
