Metadata-Version: 2.4
Name: watchinotify
Version: 0.1.0
Summary: Simple and powerfull file watcher using libc's inotify
Author-email: Corentin <corentin@ayo.tokyo>
License-Expression: GPL-3.0-or-later
Project-URL: Homepage, https://codeberg.org/corentin-pro/watchinotify
Project-URL: Issues, https://codeberg.org/corentin-pro/watchinotify/issues
Classifier: Programming Language :: Python :: 3
Classifier: Operating System :: POSIX :: Linux
Requires-Python: >=3.10
License-File: LICENSE
Provides-Extra: test
Requires-Dist: pytest; extra == "test"
Dynamic: license-file
